{
  "version": 1,
  "serviceConfiguration": {
    "apiName": "brevityapp",
    "serviceName": "AppSync",
    "gqlSchemaPath": "/tmp/amplify-fa8b2dfe-1c90-480f-a737-cb6a3a043cc8/amplify/backend/api/brevityapp/schema.graphql",
    "defaultAuthType": {
      "mode": "API_KEY",
      "keyDescription": "api key description",
      "expirationTime": 30
    },
    "additionalAuthTypes": [
      {
        "mode": "AWS_IAM"
      }
    ],
    "conflictResolution": {
      "defaultResolutionStrategy": {
        "type": "AUTOMERGE"
      }
    }
  }
}